[
	{
		"text": "' Ys",
		"box": [
			{
				"x": 562,
				"y": 12
			},
			{
				"x": 746,
				"y": 12
			},
			{
				"x": 746,
				"y": 136
			},
			{
				"x": 562,
				"y": 136
			}
		],
		"label": "",
		"id": 1
	},
	{
		"text": "Chef",
		"box": [
			{
				"x": 46,
				"y": 162
			},
			{
				"x": 112,
				"y": 162
			},
			{
				"x": 112,
				"y": 194
			},
			{
				"x": 46,
				"y": 194
			}
		],
		"label": "",
		"id": 2
	},
	{
		"text": "심 정 섭 Sim Jeong Seob",
		"box": [
			{
				"x": 44,
				"y": 206
			},
			{
				"x": 382,
				"y": 206
			},
			{
				"x": 382,
				"y": 254
			},
			{
				"x": 44,
				"y": 254
			}
		],
		"label": "",
		"id": 3
	},
	{
		"text": "서울특별시 서초구 서초대로 254 오퓨런스 빌딩 '총 IF, 254, Seucho-daero, Seocho-gu, Seoul, Repubic of Kcresi T. 02-522-4500 M. 010-2111-8933 E. sub3046@naver.com",
		"box": [
			{
				"x": 45,
				"y": 277
			},
			{
				"x": 639,
				"y": 277
			},
			{
				"x": 639,
				"y": 370
			},
			{
				"x": 45,
				"y": 370
			}
		],
		"label": "",
		"id": 4
	},
	{
		"text": "www.sushisora.co.kr",
		"box": [
			{
				"x": 46,
				"y": 372
			},
			{
				"x": 260,
				"y": 372
			},
			{
				"x": 260,
				"y": 400
			},
			{
				"x": 46,
				"y": 400
			}
		],
		"label": "",
		"id": 5
	}
]